binance_reporting/__init__.py
binance_reporting/downloader.py
binance_reporting/helper.py
binance_reporting/start.py
binance_reporting/ticker.py
binance_reporting-0.2.0.2.dist-info/LICENSE
binance_reporting-0.2.0.2.dist-info/METADATA
binance_reporting-0.2.0.2.dist-info/WHEEL
binance_reporting-0.2.0.2.dist-info/top_level.txt
binance_reporting-0.2.0.2.dist-info/RECORD
