Metadata-Version: 2.1
Name: binance-reporting
Version: 0.2.0.2
Summary: Binance Reporting Library
Home-page: https://binance-reporting.readthedocs.io/en/latest/
Author: Jan Abraham
Author-email: jan.abraham@bluewin.ch
License: OSI Approved :: GNU General Public License v3 (GPLv3)
Project-URL: Documentation, https://binance-reporting.readthedocs.io/en/latest/
Project-URL: Source Code, https://github.com/JanAbraham/binance-reporting
Project-URL: Bug Tracker, https://github.com/JanAbraham/binance-reporting/issues
Platform: Windows
Platform: Linux
Platform: MacOS
Classifier: Programming Language :: Python :: 3
Classifier: License :: OSI Approved :: GNU General Public License v3 (GPLv3)
Classifier: Operating System :: OS Independent
Requires-Python: >=3.9
License-File: LICENSE
Requires-Dist: pyyaml
Requires-Dist: pandas
Requires-Dist: python-telegram-bot
Requires-Dist: python-binance
Requires-Dist: finta
